ksamsok/__init__.py
ksamsok/ksamsok.py
ksamsok-0.8.0.dist-info/LICENSE
ksamsok-0.8.0.dist-info/METADATA
ksamsok-0.8.0.dist-info/WHEEL
ksamsok-0.8.0.dist-info/top_level.txt
ksamsok-0.8.0.dist-info/RECORD
